<?xml version="1.0" encoding="UTF-8"?><nfeProc versao="4.00" xmlns="http://www.portalfiscal.inf.br/nfe"><NFe xmlns="http://www.portalfiscal.inf.br/nfe"><infNFe Id="NFe42220878515624000805550180000957971290718989" versao="4.00"><ide><cUF>42</cUF><cNF>29071898</cNF><natOp>5102-VENDA DE MERC.ADQ.OU RECEB.DE TERC.</natOp><mod>55</mod><serie>18</serie><nNF>95797</nNF><dhEmi>2022-08-16T10:19:35-03:00</dhEmi><dhSaiEnt>2022-08-16T10:19:35-03:00</dhSaiEnt><tpNF>1</tpNF><idDest>1</idDest><cMunFG>4218202</cMunFG><tpImp>1</tpImp><tpEmis>1</tpEmis><cDV>9</cDV><tpAmb>1</tpAmb><finNFe>1</finNFe><indFinal>1</indFinal><indPres>1</indPres><indIntermed>0</indIntermed><procEmi>0</procEmi><verProc>3.23</verProc></ide><emit><CNPJ>78515624000805</CNPJ><xNome>CONSTRUCOLOR TIMBO</xNome><xFant>CONSTRUCOLOR TIMBO</xFant><enderEmit><xLgr>RUA BLUMENAU</xLgr><nro>594</nro><xBairro>ESTADOS</xBairro><cMun>4218202</cMun><xMun>TIMBO</xMun><UF>SC</UF><CEP>89120000</CEP><cPais>1058</cPais><xPais>BRASIL</xPais><fone>4733951011</fone></enderEmit><IE>257620613</IE><CRT>3</CRT></emit><dest><CPF>50161652972</CPF><xNome>HARRO ROBERTO GUTZ</xNome><enderDest><xLgr>R CHILE</xLgr><nro>170</nro><xBairro>IMIGRANTES</xBairro><cMun>4218202</cMun><xMun>TIMBO</xMun><UF>SC</UF><CEP>89120000</CEP><cPais>1058</cPais><xPais>BRASIL</xPais><fone>4733820269</fone></enderDest><indIEDest>9</indIEDest><email>HARRO.GUTZ@GMAIL.COM</email></dest><det nItem="1"><prod><cProd>2545</cProd><cEAN>SEM GTIN</cEAN><xProd>GESSO JUNTA LIDER 1KG</xProd><NCM>25202090</NCM><CFOP>5102</CFOP><uCom>KG</uCom><qCom>1.0000</qCom><vUnCom>5.90000</vUnCom><vProd>5.90</vProd><cEANTrib>SEM GTIN</cEANTrib><uTrib>KG</uTrib><qTrib>1.0000</qTrib><vUnTrib>5.90000</vUnTrib><indTot>1</indTot><xPed>GIROLA</xPed></prod><imposto><vTotTrib>0.25</vTotTrib><ICMS><ICMS00><orig>0</orig><CST>00</CST><modBC>3</modBC><vBC>5.90</vBC><pICMS>17.00</pICMS><vICMS>1.00</vICMS></ICMS00></ICMS><IPI><cEnq>999</cEnq><IPITrib><CST>99</CST><vBC>0.00</vBC><pIPI>0.00</pIPI><vIPI>0.00</vIPI></IPITrib></IPI><PIS><PISAliq><CST>01</CST><vBC>4.90</vBC><pPIS>1.65</pPIS><vPIS>0.08</vPIS></PISAliq></PIS><COFINS><COFINSAliq><CST>01</CST><vBC>4.90</vBC><pCOFINS>7.60</pCOFINS><vCOFINS>0.37</vCOFINS></COFINSAliq></COFINS></imposto></det><det nItem="2"><prod><cProd>1801.4</cProd><cEAN>SEM GTIN</cEAN><xProd>LUKSSEDA BASE A 0,8 LTS. A526 NUVEM DE PAPEL SEDA MAQLUKS (DOSADO 2X)</xProd><NCM>32091010</NCM><CEST>2400100</CEST><CFOP>5102</CFOP><uCom>KG</uCom><qCom>1.0000</qCom><vUnCom>44.00000</vUnCom><vProd>44.00</vProd><cEANTrib>SEM GTIN</cEANTrib><uTrib>KG</uTrib><qTrib>1.0000</qTrib><vUnTrib>44.00000</vUnTrib><indTot>1</indTot><xPed>GIROLA</xPed></prod><imposto><vTotTrib>13.40</vTotTrib><ICMS><ICMS00><orig>0</orig><CST>00</CST><modBC>3</modBC><vBC>44.00</vBC><pICMS>17.00</pICMS><vICMS>7.48</vICMS></ICMS00></ICMS><IPI><cEnq>999</cEnq><IPITrib><CST>99</CST><vBC>0.00</vBC><pIPI>0.00</pIPI><vIPI>0.00</vIPI></IPITrib></IPI><PIS><PISAliq><CST>01</CST><vBC>36.52</vBC><pPIS>1.65</pPIS><vPIS>0.60</vPIS></PISAliq></PIS><COFINS><COFINSAliq><CST>01</CST><vBC>36.52</vBC><pCOFINS>7.60</pCOFINS><vCOFINS>2.78</vCOFINS></COFINSAliq></COFINS></imposto></det><det nItem="3"><prod><cProd>533.1.38</cProd><cEAN>SEM GTIN</cEAN><xProd>MASSA ACRILICA DACAR REFIL BRANCO 15 KGS</xProd><NCM>32141020</NCM><CEST>1000300</CEST><CFOP>5102</CFOP><uCom>PCT</uCom><qCom>3.0000</qCom><vUnCom>58.90000</vUnCom><vProd>176.70</vProd><cEANTrib>SEM GTIN</cEANTrib><uTrib>PCT</uTrib><qTrib>3.0000</qTrib><vUnTrib>58.90000</vUnTrib><indTot>1</indTot><xPed>GIROLA</xPed></prod><imposto><vTotTrib>56.05</vTotTrib><ICMS><ICMS00><orig>0</orig><CST>00</CST><modBC>3</modBC><vBC>176.70</vBC><pICMS>17.00</pICMS><vICMS>30.04</vICMS></ICMS00></ICMS><IPI><cEnq>999</cEnq><IPITrib><CST>99</CST><vBC>0.00</vBC><pIPI>0.00</pIPI><vIPI>0.00</vIPI></IPITrib></IPI><PIS><PISAliq><CST>01</CST><vBC>146.66</vBC><pPIS>1.65</pPIS><vPIS>2.42</vPIS></PISAliq></PIS><COFINS><COFINSAliq><CST>01</CST><vBC>146.66</vBC><pCOFINS>7.60</pCOFINS><vCOFINS>11.15</vCOFINS></COFINSAliq></COFINS></imposto></det><total><ICMSTot><vBC>226.60</vBC><vICMS>38.52</vICMS><vICMSDeson>0.00</vICMSDeson><vFCP>0.00</vFCP><vBCST>0.00</vBCST><vST>0.00</vST><vFCPST>0.00</vFCPST><vFCPSTRet>0.00</vFCPSTRet><vProd>226.60</vProd><vFrete>0.00</vFrete><vSeg>0.00</vSeg><vDesc>0.00</vDesc><vII>0.00</vII><vIPI>0.00</vIPI><vIPIDevol>0.00</vIPIDevol><vPIS>3.10</vPIS><vCOFINS>14.30</vCOFINS><vOutro>0.00</vOutro><vNF>226.60</vNF><vTotTrib>69.70</vTotTrib></ICMSTot></total><transp><modFrete>0</modFrete><vol><qVol>5</qVol><pesoL>46.910</pesoL><pesoB>47.210</pesoB></vol></transp><cobr><fat><nFat>00095797/01</nFat><vOrig>226.60</vOrig><vDesc>0.00</vDesc><vLiq>226.60</vLiq></fat><dup><nDup>001</nDup><dVenc>2022-08-22</dVenc><vDup>226.60</vDup></dup></cobr><pag><detPag><indPag>0</indPag><tPag>99</tPag><xPag>A DEFINIR</xPag><vPag>226.60</vPag></detPag></pag><infAdic><infCpl>MD5 CB-ECF: 596127382FBD8B287267A6F0A2D1842F|ICMS DESCONSIDERADO NA BC DE PIS E COFINS CONFORME (RE) 574.706/PR E PARECER SEI NO 7.698/2021||TRIB APROX R$: 32.18(FED.), 37.52(EST.) FONTE: IBPT/EMPRESOMETRO.COM.BR       M2L5P8 O CARREGAMENTO, DESCARREGAMENTO, TRANSBORDO E TRANSPORTE E RESPONSABILIDADE DO TRANSPORTADOR.|AUT VIA WHATS COM SR HARRO|PEDIDO CLIENTE: GIROLA |VENDEDOR: 1148-ALLANDEIVED CAMARGO|OBRA: CASA  TESTE COR INTERNA|TITULOS: 4734790|TIPO COBR.: 4-DEPOSITO|CELULAR: 47 98444-0178</infCpl><obsCont xCampo="appnameandversion"><xTexto>TutomNFe|3.23</xTexto></obsCont><obsCont xCampo="codcliente"><xTexto>187888</xTexto></obsCont><obsCont xCampo="website"><xTexto>www.construcolor.com.br</xTexto></obsCont><obsCont xCampo="tipocob"><xTexto>4-DEPOSITO</xTexto></obsCont><obsCont xCampo="infoemit"><xTexto>vendas.timbo@construcolor.com.br^</xTexto></obsCont></infAdic><compra><xPed>GIROLA</xPed></compra><infRespTec><CNPJ>73241333000186</CNPJ><xContato>CLAUDIO J BRETZKE</xContato><email>desenv@cbsistemas.com.br</email><fone>4730414321</fone></infRespTec></infNFe><Signature xmlns="http://www.w3.org/2000/09/xmldsig#"><SignedInfo><CanonicalizationMethod Algorithm="http://www.w3.org/TR/2001/REC-xml-c14n-20010315"/><SignatureMethod Algorithm="http://www.w3.org/2000/09/xmldsig#rsa-sha1"/><Reference URI="#NFe42220878515624000805550180000957971290718989"><Transforms><Transform Algorithm="http://www.w3.org/2000/09/xmldsig#enveloped-signature"/><Transform Algorithm="http://www.w3.org/TR/2001/REC-xml-c14n-20010315"/></Transforms><DigestMethod Algorithm="http://www.w3.org/2000/09/xmldsig#sha1"/><DigestValue>nc+o4PhD50czFjaMCW+Q1Pt6H2U=</DigestValue></Reference></SignedInfo><SignatureValue>HSbzG/M/423Q5eKp7OoRhvKd9eDdbZPxnswHPkN1oBzPH1psnHDhPwguu9YcTSkiMEmc7sOqi91O
FdpJ9csoB9Tl5KWKxs3FI1nNy6CfKvMG40golZsop+SjKaOQHdozlQOS8LA/m7Yy2SAmavp01Q0H
O7NOjgJ2VC6JdOC8DzxxuQ56/dxvhXWWEAL6zxeaNzdIKgBIg+uZ4bidnFPP693wIgHFNN+/257H
+6/1bOpW7W9evDPRFOaAfVIV4Hn+x8AWcEqdDLNoQ28Wk7SXm3zHN5JlwxyB14GLYNp4WYD67kiD
Bf6Aq34kkXETC2R9qHclcXYJiPQlv5iDZRLbbw==</SignatureValue><KeyInfo><X509Data><X509Certificate>MIIH/TCCBeWgAwIBAgIIK/50+KJzI8UwDQYJKoZIhvcNAQELBQAwdDELMAkGA1UEBhMCQlIxEzAR
BgNVBAoTCklDUC1CcmFzaWwxNjA0BgNVBAsTLVNlY3JldGFyaWEgZGEgUmVjZWl0YSBGZWRlcmFs
IGRvIEJyYXNpbCAtIFJGQjEYMBYGA1UEAxMPQUMgVkFMSUQgUkZCIHY1MB4XDTIyMDUwNDE1NDc0
NVoXDTIzMDUwNDE1NDc0NVowggEkMQswCQYDVQQGEwJCUjELMAkGA1UECBMCU0MxETAPBgNVBAcT
CEJMVU1FTkFVMRMwEQYDVQQKEwpJQ1AtQnJhc2lsMTYwNAYDVQQLEy1TZWNyZXRhcmlhIGRhIFJl
Y2VpdGEgRmVkZXJhbCBkbyBCcmFzaWwgLSBSRkIxFjAUBgNVBAsTDVJGQiBlLUNOUEogQTExJDAi
BgNVBAsTG0FSIE5PVk8gQ0VSVElGSUNBRE8gRElHSVRBTDETMBEGA1UECxMKUHJlc2VuY2lhbDEX
MBUGA1UECxMOMzQ3ODczNDcwMDAxNDgxPDA6BgNVBAMTM0NPTlNUUlVDT0xPUiBDT01FUkNJTyBE
RSBUSU5UQVMgTFREQTo3ODUxNTYyNDAwMDEzOTCCASIwDQYJKoZIhvcNAQEBBQADggEPADCCAQoC
ggEBAMDQP347iUtV5d5uMI+QhC3B9QP/UuKJcMJZ+Sddt17zHTImkM2DmJJ4ex4SVI/tty+Ray1F
zfCYPSZjYeK9n4xYVQqrEqYd9osoGGr8ZkZA0f6pEUknYQjgP7IAsdp+bK8ybYMbyUBfns0x9cgF
ILB9hfJbayai1+2nEtJqOT4w6+2sMG4CMyEBxUPm7cN27hpE+zqAwWtLDjg4GlQ0ZiGDGdbZoZ0A
QbAL+p4yrKuwKzN/qoREHn2vf10yaL2JvrtMOmM61hE12xDnMS2BcD+u3Z26gaYSCHzAXrhjHpg7
yPn24JtopVdjMogbI81Axgh8PseX6E8ybEwEHP8lt3sCAwEAAaOCAt8wggLbMIGcBggrBgEFBQcB
AQSBjzCBjDBVBggrBgEFBQcwAoZJaHR0cDovL2ljcC1icmFzaWwudmFsaWRjZXJ0aWZpY2Fkb3Jh
LmNvbS5ici9hYy12YWxpZHJmYi9hYy12YWxpZHJmYnY1LnA3YjAzBggrBgEFBQcwAYYnaHR0cDov
L29jc3B2NS52YWxpZGNlcnRpZmljYWRvcmEuY29tLmJyMAkGA1UdEwQCMAAwHwYDVR0jBBgwFoAU
U8ul5HVQmUAsvlsVRcm+yzCqicUwcAYDVR0gBGkwZzBlBgZgTAECASUwWzBZBggrBgEFBQcCARZN
aHR0cDovL2ljcC1icmFzaWwudmFsaWRjZXJ0aWZpY2Fkb3JhLmNvbS5ici9hYy12YWxpZHJmYi9k
cGMtYWMtdmFsaWRyZmJ2NS5wZGYwgbYGA1UdHwSBrjCBqzBToFGgT4ZNaHR0cDovL2ljcC1icmFz
aWwudmFsaWRjZXJ0aWZpY2Fkb3JhLmNvbS5ici9hYy12YWxpZHJmYi9sY3ItYWMtdmFsaWRyZmJ2
NS5jcmwwVKBSoFCGTmh0dHA6Ly9pY3AtYnJhc2lsMi52YWxpZGNlcnRpZmljYWRvcmEuY29tLmJy
L2FjLXZhbGlkcmZiL2xjci1hYy12YWxpZHJmYnY1LmNybDAOBgNVHQ8BAf8EBAMCBeAwHQYDVR0l
BBYwFAYIKwYBBQUHAwIGCCsGAQUFBwMEMIGzBgNVHREEgaswgaiBG21hcnRpbmFAY29uc3RydWNv
bG9yLmNvbS5icqA4BgVgTAEDBKAvBC0wNjAzMTk1NDE4MTcyMDE2OTcyMDAwMDAwMDAwMDAwMDAw
MDAwMDAwMDAwMDCgGwYFYEwBAwKgEgQQUkVJTkFMRE8gRklTQ0hFUqAZBgVgTAEDA6AQBA43ODUx
NTYyNDAwMDEzOaAXBgVgTAEDB6AOBAwwMDAwMDAwMDAwMDAwDQYJKoZIhvcNAQELBQADggIBAFZG
lg3BtuDYEfIJM0rgifpa7bh77dFK9d0QR3E6M+yZiSzN3cnA9RB4HTrDV1/7LvkuEasONyTvTI4N
u9XBhZ+/nl5br2cJhXOX1CLkxWpgccJbWxsfTQ4UopHU103hy/1e9T4hU9M9ooaisyYL4npD0fU+
IAu6vBwYGlaRpjTdlRROyq5ZiBnzUogNuxoLdTj9CmLhxVtxZWUBO+PcM1OK7fyBOmqMJPecnuOr
1730RnPdQjAtVY3dQwiLqa+/vAuIX7QpDEDhNmaWvHrGIwi/uxHzYABOj7sEDyDmeQRaDzacaMK3
YgPoil087vEYaBFQ79k7zXb8h9ZsTDGGuchN0L8/zDl3Es/8LrnJLFQbgFoJpPHwNyK2VgRkS8bq
ZfD5wKZqW/YDshO0r5xMvodbRN1kfLe8mDXZHGzQ4U4uQXYPFYZMfea9ClJvIR31cqSFLyC9ahP+
VTUyJpOBLyETC+vIL5es9FMyXk+hVDUZdT+XXILGRgBU52+leQythd4miXvQVu2Dv7bzf1DvSRAo
lnRV4DkBg7Hs5EK1po194hKjXpUjhoVyZ0qsf4geQbJGsxt3W7YuAzAzBDrZrPlfMaAppG9y1I9Q
/Ghv8HVTLhHAVr4CobQTh56B0DeoerEmBH+Pdu3808je4FryX6iR66TZawZlmlcdsJiHO5wC</X509Certificate></X509Data></KeyInfo></Signature></NFe><protNFe versao="4.00"><infProt><tpAmb>1</tpAmb><verAplic>SVRS202208151116</verAplic><chNFe>42220878515624000805550180000957971290718989</chNFe><dhRecbto>2022-08-16T10:20:04-03:00</dhRecbto><nProt>342220167411064</nProt><digVal>nc+o4PhD50czFjaMCW+Q1Pt6H2U=</digVal><cStat>100</cStat><xMotivo>Autorizado o uso da NF-e</xMotivo></infProt></protNFe></nfeProc>